[{"_id":"EaX9DzkYfP8popqF9","content":"card 1","time":1,"timestamp":"2016-03-18T15:36:36.783Z","event":{"id":"1","name":"Keynote"},"public":true},{"_id":"RdcZAtFyfqSK6iP6e","content":"card 2","time":2,"timestamp":"2016-03-18T15:36:36.783Z","event":{"id":"1","name":"Keynote"},"public":true},{"_id":"PxifxEaZtEzGHA3kh","content":"aasdasdasd","owner":"YDGojzXYdqreJZKS2","event":{"id":"1","name":"Keynote"},"public":true,"timestamp":"2016-03-18T15:51:23.995Z","time":14},{"_id":"FLKfy83K9TQfq8oSc","content":"asad adasdas","owner":"YDGojzXYdqreJZKS2","event":{"id":"1","name":"Keynote"},"public":true,"timestamp":"2016-03-18T15:51:30.983Z","time":4},{"_id":"hLwAceHQ9F4eQpEFC","content":"213123123","owner":"YDGojzXYdqreJZKS2","event":{"id":"1","name":"Keynote"},"public":true,"timestamp":"2016-03-18T15:51:35.895Z","time":8},{"_id":"svgBDQGCuadyfirSZ","content":"asda a asdasd","owner":"YDGojzXYdqreJZKS2","event":{"id":"1","name":"Keynote"},"public":true,"timestamp":"2016-03-18T16:06:37.817Z","time":39},{"_id":"rxDy7ebiJWmbXbkSW","content":"bsa asdsadasd","owner":"YDGojzXYdqreJZKS2","event":{"id":"1","name":"Keynote"},"public":true,"timestamp":"2016-03-18T16:20:05.834Z","time":11},{"_id":"4AzQhPPfTxbZyYDk6","content":"<span onmouseover='this.textContent=\"Hello\"' onmouseout='this.textContent=\"Howdy\"'>Is <i>anyone</i> reading this?</span>\nTHIS IS UNSAFE","owner":"YDGojzXYdqreJZKS2","event":{"id":"1","name":"Keynote"},"public":true,"timestamp":"2016-03-18T19:23:21.968Z","time":20}]